setup.py
loggly/__init__.py
loggly/connection.py
loggly/device.py
loggly/input.py
loggly.egg-info/PKG-INFO
loggly.egg-info/SOURCES.txt
loggly.egg-info/dependency_links.txt
loggly.egg-info/top_level.txt
scripts/loggly-add-device
scripts/loggly-create-input
scripts/loggly-delete-input
scripts/loggly-describe-input
scripts/loggly-remove-device